{"ongoing_trials": {"tuner0": "06"}, "hyperparameters": {"space": [{"class_name": "Int", "config": {"name": "units_input", "default": null, "conditions": [], "min_value": 16, "max_value": 124, "step": 16, "sampling": "linear"}}, {"class_name": "Int", "config": {"name": "units_hidden", "default": null, "conditions": [], "min_value": 16, "max_value": 124, "step": 16, "sampling": "linear"}}, {"class_name": "Choice", "config": {"name": "learning_rate", "default": 0.01, "conditions": [], "values": [0.01, 0.001, 0.0001], "ordered": true}}], "values": {"units_input": 16, "units_hidden": 16, "learning_rate": 0.01}}, "start_order": ["00", "01", "02", "03", "04", "05", "06"], "end_order": ["00", "01", "02", "03", "04", "05"], "run_times": {"00": 1, "01": 1, "02": 1, "03": 1, "04": 1, "05": 1}, "retry_queue": [], "seed": 5223, "seed_state": 5244, "tried_so_far": ["165824df723751cc94f9b46c68450710", "cad94c9236c4714d62d74529d6d02492", "14a79194031bd85349ee100041b3f48e", "dc9085da9656f07c0e3d5ae4e0184c1b", "8c20a16ffbcda58d32ec379f6643ee34", "0584aee07d7e411426bdb684c5f2688d", "a42a7c311c241ca836b16b9c0a615121"], "id_to_hash": {"00": "a42a7c311c241ca836b16b9c0a615121", "01": "dc9085da9656f07c0e3d5ae4e0184c1b", "02": "8c20a16ffbcda58d32ec379f6643ee34", "03": "0584aee07d7e411426bdb684c5f2688d", "04": "cad94c9236c4714d62d74529d6d02492", "05": "14a79194031bd85349ee100041b3f48e", "06": "165824df723751cc94f9b46c68450710"}, "display": {"search_start": "2024-02-14T15:04:43.279296", "trial_start": {"00": "2024-02-14T15:04:43.279296", "01": "2024-02-14T15:05:59.208296", "02": "2024-02-14T15:07:43.755296", "03": "2024-02-14T15:09:36.938494", "04": "2024-02-14T15:11:34.586839", "05": "2024-02-14T15:13:01.312838"}, "trial_number": {"00": 1, "01": 2, "02": 3, "03": 4, "04": 5, "05": 6}}}